transpose_dict/__init__.py
transpose_dict/__version__.py
transpose_dict/transpose_dict.py
transpose_dict-1.0.0.dist-info/LICENSE
transpose_dict-1.0.0.dist-info/METADATA
transpose_dict-1.0.0.dist-info/WHEEL
transpose_dict-1.0.0.dist-info/top_level.txt
transpose_dict-1.0.0.dist-info/RECORD
